{
  "$schema": "https://git.carvel.li/liza/Questionable/raw/branch/master/QuestPaths/quest-v1.json",
  "Author": "JerryWester",
  "QuestSequence": [
    {
      "Sequence": 0,
      "Steps": [
        {
          "DataId": 1006690,
          "Position": {
            "X": 39.261353,
            "Y": 1.2148079,
            "Z": 0.8086548
          },
          "TerritoryId": 212,
          "InteractionType": "AcceptQuest"
        }
      ]
    },
    {
      "Sequence": 1,
      "Steps": [
        {
          "DataId": 2001717,
          "Position": {
            "X": 25.497803,
            "Y": 2.090454,
            "Z": -0.015319824
          },
          "TerritoryId": 212,
          "InteractionType": "Interact",
          "TargetTerritoryId": 212
        },
        {
          "DataId": 2001716,
          "Position": {
            "X": -15.701599,
            "Y": 1.083313,
            "Z": -0.015319824
          },
          "TerritoryId": 212,
          "InteractionType": "Interact",
          "TargetTerritoryId": 140
        },
        {
          "DataId": 1006578,
          "Position": {
            "X": -467.27704,
            "Y": 22.996977,
            "Z": -475.21173
          },
          "TerritoryId": 140,
          "InteractionType": "Interact"
        }
      ]
    },
    {
      "Sequence": 2,
      "Steps": [
        {
          "DataId": 1006633,
          "Position": {
            "X": -396.7804,
            "Y": 27.883184,
            "Z": -739.3149
          },
          "TerritoryId": 140,
          "InteractionType": "Interact"
        }
      ]
    },
    {
      "Sequence": 3,
      "Steps": [
        {
          "DataId": 2002252,
          "Position": {
            "X": -662.25684,
            "Y": 62.333008,
            "Z": -805.478
          },
          "TerritoryId": 140,
          "InteractionType": "SinglePlayerDuty"
        }
      ]
    },
    {
      "Sequence": 255,
      "Steps": [
        {
          "DataId": 1006578,
          "Position": {
            "X": -467.27704,
            "Y": 22.996977,
            "Z": -475.21173
          },
          "StopDistance": 7,
          "TerritoryId": 140,
          "InteractionType": "CompleteQuest"
        }
      ]
    }
  ]
}
