{
  "$schema": "https://git.carvel.li/liza/Questionable/raw/branch/master/QuestPaths/quest-v1.json",
  "Author": "liza",
  "QuestSequence": [
    {
      "Sequence": 0,
      "Steps": [
        {
          "DataId": 1000972,
          "Position": {
            "X": 20.279175,
            "Y": 40.19993,
            "Z": -6.1189575
          },
          "TerritoryId": 128,
          "InteractionType": "AcceptQuest"
        }
      ]
    },
    {
      "Sequence": 255,
      "Steps": [
        {
          "DataId": 1003239,
          "Position": {
            "X": -283.68048,
            "Y": 10.593393,
            "Z": -249.34778
          },
          "TerritoryId": 134,
          "InteractionType": "CompleteQuest",
          "AethernetShortcut": [
            "[Limsa Lominsa] The Aftcastle",
            "[Limsa Lominsa] Zephyr Gate (Middle La Noscea)"
          ]
        }
      ]
    }
  ]
}
